chat2plot/__init__.py
chat2plot/chat2plot.py
chat2plot/dataset_description.py
chat2plot/dictionary_helper.py
chat2plot/prompt.py
chat2plot/render.py
chat2plot/schema.py
chat2plot/transform.py
chat2plot/version.py
tests/__init__.py
tests/test_chat2plot.py
tests/test_schema.py
chat2plot-0.0.11.dist-info/LICENSE
chat2plot-0.0.11.dist-info/METADATA
chat2plot-0.0.11.dist-info/WHEEL
chat2plot-0.0.11.dist-info/top_level.txt
chat2plot-0.0.11.dist-info/RECORD
